[
  {
    "exchange": "belo",
    "moneda": "USD",
    "monedaBase": "BRL",
    "criptomoneda": "USDT",
    "criptomonedaBase": null,
    "compra": 0.18225377107364685,
    "venta": 0.17088174982911825
  },
  {
    "exchange": "fiwind",
    "moneda": "USD",
    "monedaBase": "BRL",
    "criptomoneda": null,
    "criptomonedaBase": "USDT",
    "compra": 0.179209,
    "venta": 0.171185
  },
  {
    "exchange": "cocos",
    "moneda": "USD",
    "monedaBase": "BRL",
    "criptomoneda": "USDT",
    "criptomonedaBase": null,
    "compra": 0.177769,
    "venta": null
  },
  {
    "exchange": "takenos",
    "moneda": "USD",
    "monedaBase": "BRL",
    "criptomoneda": null,
    "criptomonedaBase": "USDT",
    "compra": 0.181211311724718,
    "venta": 0.16952298774094515
  },
  {
    "exchange": "satoshitango",
    "moneda": "USD",
    "monedaBase": "BRL",
    "criptomoneda": "USDT",
    "criptomonedaBase": null,
    "compra": 0.1798561151079137,
    "venta": null
  },
  {
    "exchange": "satoshitango",
    "moneda": "USD",
    "monedaBase": "BRL",
    "criptomoneda": "USD",
    "criptomonedaBase": null,
    "compra": 0.19,
    "venta": null
  },
  {
    "exchange": "prex",
    "moneda": "USD",
    "monedaBase": "BRL",
    "compra": 0.17953321364452424,
    "venta": null
  },
  {
    "exchange": "plus",
    "moneda": "USD",
    "monedaBase": "BRL",
    "criptomoneda": "USDT",
    "criptomonedaBase": null,
    "compra": 0.17889087656529518,
    "venta": null
  },
  {
    "exchange": "astropay",
    "moneda": "USD",
    "monedaBase": "BRL",
    "compra": 0.17997003,
    "venta": null
  }
]