[
  {
    "exchange": "belo",
    "moneda": "BRL",
    "monedaBase": "ARS",
    "compra": 0.0033761164059694783,
    "venta": 0.003560655737704918
  },
  {
    "exchange": "fiwind",
    "moneda": "BRL",
    "monedaBase": "ARS",
    "compra": 0.0033983999136969548,
    "venta": 0.003646207149326921
  },
  {
    "exchange": "dolarapp",
    "moneda": "BRL",
    "monedaBase": "ARS",
    "compra": 0.0034786294017048924,
    "venta": null
  },
  {
    "exchange": "satoshitango",
    "moneda": "BRL",
    "monedaBase": "ARS",
    "compra": 0.0034883315310287087,
    "venta": null
  },
  {
    "exchange": "prex",
    "moneda": "BRL",
    "monedaBase": "ARS",
    "compra": 0.0034097108565193674,
    "venta": null
  },
  {
    "exchange": "lemon",
    "moneda": "BRL",
    "monedaBase": "ARS",
    "compra": 0.003419504855696895,
    "venta": null
  },
  {
    "exchange": "plus",
    "moneda": "BRL",
    "monedaBase": "ARS",
    "compra": 0.0034139014065273795,
    "venta": null
  },
  {
    "exchange": "astropay",
    "moneda": "BRL",
    "monedaBase": "ARS",
    "compra": 0.003499733068044458,
    "venta": null
  }
]