[
  {
    "exchange": "belo",
    "moneda": "BRL",
    "monedaBase": "ARS",
    "compra": 0.0034004641633582984,
    "venta": 0.0035961930659415367
  },
  {
    "exchange": "fiwind",
    "moneda": "BRL",
    "monedaBase": "ARS",
    "compra": 0.003425755078127787,
    "venta": 0.003674683489681256
  },
  {
    "exchange": "dolarapp",
    "moneda": "BRL",
    "monedaBase": "ARS",
    "compra": 0.0035264262790103557,
    "venta": null
  },
  {
    "exchange": "satoshitango",
    "moneda": "BRL",
    "monedaBase": "ARS",
    "compra": 0.003501891021151422,
    "venta": null
  },
  {
    "exchange": "prex",
    "moneda": "BRL",
    "monedaBase": "ARS",
    "compra": 0.003415396196204948,
    "venta": null
  },
  {
    "exchange": "lemon",
    "moneda": "BRL",
    "monedaBase": "ARS",
    "compra": 0.0034250094187759012,
    "venta": null
  },
  {
    "exchange": "plus",
    "moneda": "BRL",
    "monedaBase": "ARS",
    "compra": 0.003446018126055343,
    "venta": null
  },
  {
    "exchange": "astropay",
    "moneda": "BRL",
    "monedaBase": "ARS",
    "compra": 0.0035711224903923794,
    "venta": null
  }
]