[
  {
    "exchange": "belo",
    "moneda": "BRL",
    "monedaBase": "ARS",
    "compra": 0.0038861584181049263,
    "venta": 0.004209811320754717
  },
  {
    "exchange": "fiwind",
    "moneda": "BRL",
    "monedaBase": "ARS",
    "compra": 0.003984329536309785,
    "venta": 0.004209321687678029
  },
  {
    "exchange": "cocos",
    "moneda": "BRL",
    "monedaBase": "ARS",
    "compra": 0.004010605789955964,
    "venta": null
  },
  {
    "exchange": "dolarapp",
    "moneda": "BRL",
    "monedaBase": "ARS",
    "compra": 0.00403228069070389,
    "venta": null
  },
  {
    "exchange": "satoshitango",
    "moneda": "BRL",
    "monedaBase": "ARS",
    "compra": 0.003988990386533169,
    "venta": null
  },
  {
    "exchange": "prex",
    "moneda": "BRL",
    "monedaBase": "ARS",
    "compra": 0.003999766413641443,
    "venta": null
  },
  {
    "exchange": "lemon",
    "moneda": "BRL",
    "monedaBase": "ARS",
    "compra": 0.003965107057890563,
    "venta": null
  },
  {
    "exchange": "plus",
    "moneda": "BRL",
    "monedaBase": "ARS",
    "compra": 0.003976933784052496,
    "venta": null
  },
  {
    "exchange": "astropay",
    "moneda": "BRL",
    "monedaBase": "ARS",
    "compra": 0.004074437704631193,
    "venta": null
  }
]