[
  {
    "exchange": "belo",
    "moneda": "BRL",
    "monedaBase": "ARS",
    "compra": 0.00320477822094749,
    "venta": 0.003375924680564896
  },
  {
    "exchange": "fiwind",
    "moneda": "BRL",
    "monedaBase": "ARS",
    "compra": 0.003221508678452833,
    "venta": 0.0034531620267996108
  },
  {
    "exchange": "dolarapp",
    "moneda": "BRL",
    "monedaBase": "ARS",
    "compra": 0.0033217126913626504,
    "venta": null
  },
  {
    "exchange": "satoshitango",
    "moneda": "BRL",
    "monedaBase": "ARS",
    "compra": 0.0033211557622052474,
    "venta": null
  },
  {
    "exchange": "prex",
    "moneda": "BRL",
    "monedaBase": "ARS",
    "compra": 0.003156042638136041,
    "venta": null
  },
  {
    "exchange": "lemon",
    "moneda": "BRL",
    "monedaBase": "ARS",
    "compra": 0.003216571777799222,
    "venta": null
  },
  {
    "exchange": "plus",
    "moneda": "BRL",
    "monedaBase": "ARS",
    "compra": 0.0032155374770892952,
    "venta": null
  },
  {
    "exchange": "astropay",
    "moneda": "BRL",
    "monedaBase": "ARS",
    "compra": 0.0033195195247280153,
    "venta": null
  }
]