[
  {
    "exchange": "belo",
    "moneda": "ARS",
    "monedaBase": "MEXt",
    "compra": 84.26143561296239,
    "venta": 79.75368529411764
  },
  {
    "exchange": "belo",
    "moneda": "BRAt",
    "monedaBase": "MEXt",
    "compra": 0.2978304474515156,
    "venta": 0.2817415411764706
  },
  {
    "exchange": "belo",
    "moneda": "ARGt",
    "monedaBase": "MEXt",
    "compra": 84.26143561296239,
    "venta": 79.75368529411764
  },
  {
    "exchange": "belo",
    "moneda": "MEXt",
    "monedaBase": "MEXt",
    "compra": 1,
    "venta": 1
  },
  {
    "exchange": "belo",
    "moneda": "CHLt",
    "monedaBase": "MEXt",
    "compra": 53.78066217447631,
    "venta": 49.34739419728094
  },
  {
    "exchange": "belo",
    "moneda": "COLt",
    "monedaBase": "MEXt",
    "compra": 214.03882285788663,
    "venta": 193.82788295014942
  },
  {
    "exchange": "belo",
    "moneda": "BOLt",
    "monedaBase": "MEXt",
    "compra": 0.5451840731998934,
    "venta": 0.4922112426
  }
]