[
  {
    "moneda": "ARS",
    "nombre": "Peso Argentino",
    "compra": 0.64,
    "venta": 0.66,
    "ultimoCierre": 0.65,
    "fechaActualizacion": "2025-11-06T16:02:39.476Z"
  },
  {
    "moneda": "USD",
    "nombre": "Dólar",
    "compra": 942.68942,
    "venta": 943.08943,
    "ultimoCierre": 942.79942,
    "fechaActualizacion": "2025-11-06T16:02:53.761Z"
  },
  {
    "moneda": "EUR",
    "nombre": "Euro",
    "compra": 1.07,
    "venta": 1.098,
    "ultimoCierre": 1.088,
    "fechaActualizacion": "2025-11-06T16:02:39.475Z"
  },
  {
    "moneda": "BRL",
    "nombre": "Real Brasileño",
    "compra": 176.126176,
    "venta": 176.2176,
    "ultimoCierre": 176.26176,
    "fechaActualizacion": "2025-11-06T16:00:04.184Z"
  },
  {
    "moneda": "UYU",
    "nombre": "Peso Uruguayo",
    "compra": 23.6823,
    "venta": 23.6923,
    "ultimoCierre": 23.7323,
    "fechaActualizacion": "2025-11-06T16:00:04.184Z"
  }
]