[
  {
    "moneda": "ARS",
    "nombre": "Peso Argentino",
    "compra": 0.99,
    "venta": 0.99,
    "ultimoCierre": 0.98,
    "fechaActualizacion": "2024-07-15T14:37:19.000Z"
  },
  {
    "moneda": "USD",
    "nombre": "Dólar",
    "compra": 908.91,
    "venta": 909.51,
    "ultimoCierre": 905.11,
    "fechaActualizacion": "2024-07-15T14:59:20.000Z"
  },
  {
    "moneda": "EUR",
    "nombre": "Euro",
    "compra": 974.35,
    "venta": 1.002,
    "ultimoCierre": 995.79,
    "fechaActualizacion": "2024-07-15T14:51:29.000Z"
  },
  {
    "moneda": "BRL",
    "nombre": "Real Brasileño",
    "compra": 166.389,
    "venta": 166.48,
    "ultimoCierre": 166.861,
    "fechaActualizacion": "2024-07-15T14:59:25.000Z"
  },
  {
    "moneda": "UYU",
    "nombre": "Peso Uruguayo",
    "compra": 22.7,
    "venta": 22.71,
    "ultimoCierre": 22.59,
    "fechaActualizacion": "2024-07-15T15:00:19.000Z"
  }
]