[
  {
    "moneda": "ARS",
    "nombre": "Peso Argentino",
    "compra": 0.75,
    "venta": 0.77,
    "ultimoCierre": 0.75,
    "fechaActualizacion": "2025-07-23T19:01:20.434Z"
  },
  {
    "moneda": "USD",
    "nombre": "Dólar",
    "compra": 948.99,
    "venta": 949.85,
    "ultimoCierre": 948.9,
    "fechaActualizacion": "2025-07-23T18:59:41.000Z"
  },
  {
    "moneda": "EUR",
    "nombre": "Euro",
    "compra": 1.101,
    "venta": 1.129,
    "ultimoCierre": 1.117,
    "fechaActualizacion": "2025-07-23T19:01:20.434Z"
  },
  {
    "moneda": "BRL",
    "nombre": "Real Brasileño",
    "compra": 172.012,
    "venta": 172.168,
    "ultimoCierre": 170.725,
    "fechaActualizacion": "2025-07-23T19:00:16.249Z"
  },
  {
    "moneda": "UYU",
    "nombre": "Peso Uruguayo",
    "compra": 23.61,
    "venta": 23.63,
    "ultimoCierre": 23.53,
    "fechaActualizacion": "2025-07-23T18:59:16.117Z"
  }
]