[
  {
    "exchange": "belo",
    "moneda": "ARS",
    "monedaBase": "BTC",
    "compra": 95419638.2334,
    "venta": 92254135.1292
  },
  {
    "exchange": "belo",
    "moneda": "BRLa",
    "monedaBase": "BTC",
    "compra": 338459.83548,
    "venta": 327291.641226
  },
  {
    "exchange": "belo",
    "moneda": "ARGt",
    "monedaBase": "BTC",
    "compra": 95419638.2334,
    "venta": 92254135.1292
  },
  {
    "exchange": "belo",
    "moneda": "ETH",
    "monedaBase": "BTC",
    "compra": 35.13394817742644,
    "venta": 34.42625208278825
  },
  {
    "exchange": "belo",
    "moneda": "USD",
    "monedaBase": "BTC",
    "criptomoneda": "USDT",
    "criptomonedaBase": null,
    "compra": 65088.4299,
    "venta": 63799.5402
  },
  {
    "exchange": "belo",
    "moneda": "USD",
    "monedaBase": "BTC",
    "criptomoneda": "USDC",
    "criptomonedaBase": null,
    "compra": 65087.4401,
    "venta": 63798.57
  },
  {
    "exchange": "belo",
    "moneda": "SOL",
    "monedaBase": "BTC",
    "compra": 829.1750206049993,
    "venta": 812.6890009857917
  },
  {
    "exchange": "belo",
    "moneda": "BRLa",
    "monedaBase": "BTC",
    "compra": 338459.83548,
    "venta": 327291.641226
  }
]