[
  {
    "exchange": "belo",
    "moneda": "ARS",
    "monedaBase": "BTC",
    "compra": 109163742.7461,
    "venta": 105274839.4038
  },
  {
    "exchange": "belo",
    "moneda": "ETH",
    "monedaBase": "BTC",
    "compra": 36.55812559178466,
    "venta": 35.821237695404854
  },
  {
    "exchange": "belo",
    "moneda": "DAI",
    "monedaBase": "BTC",
    "compra": 88159.07475439463,
    "venta": 86145.8656419603
  },
  {
    "exchange": "belo",
    "moneda": "USD",
    "monedaBase": "BTC",
    "criptomoneda": "USDT",
    "criptomonedaBase": null,
    "compra": 88106.3299,
    "venta": 86361.6402
  },
  {
    "exchange": "belo",
    "moneda": "USD",
    "monedaBase": "BTC",
    "criptomoneda": "USDC",
    "criptomonedaBase": null,
    "compra": 87958.8699,
    "venta": 86217.1002
  }
]