[
  {
    "exchange": "belo",
    "moneda": "ARS",
    "monedaBase": "BTC",
    "compra": 153309846.2599,
    "venta": 147980494.5696
  },
  {
    "exchange": "belo",
    "moneda": "ETH",
    "monedaBase": "BTC",
    "compra": 30.8333641666975,
    "venta": 30.21357979557492
  },
  {
    "exchange": "belo",
    "moneda": "USD",
    "monedaBase": "BTC",
    "criptomoneda": "USDT",
    "criptomonedaBase": null,
    "compra": 101731.8157,
    "venta": 99717.3144
  },
  {
    "exchange": "belo",
    "moneda": "USD",
    "monedaBase": "BTC",
    "criptomoneda": "USDC",
    "criptomonedaBase": null,
    "compra": 101738.8251,
    "venta": 99724.185
  },
  {
    "exchange": "belo",
    "moneda": "SOL",
    "monedaBase": "BTC",
    "compra": 655.5266468304303,
    "venta": 642.5042244652759
  },
  {
    "exchange": "belo",
    "moneda": "BRLa",
    "monedaBase": "BTC",
    "compra": 557490.350036,
    "venta": 537476.324616
  }
]