[
  {
    "exchange": "belo",
    "moneda": "ARS",
    "monedaBase": "BTC",
    "compra": 114869268.7627,
    "venta": 111082262.9202
  },
  {
    "exchange": "belo",
    "moneda": "BRAt",
    "monedaBase": "BTC",
    "compra": 387269.126386,
    "venta": 374307.14871
  },
  {
    "exchange": "belo",
    "moneda": "ARGt",
    "monedaBase": "BTC",
    "compra": 114869268.7627,
    "venta": 111082262.9202
  },
  {
    "exchange": "belo",
    "moneda": "MEXt",
    "monedaBase": "BTC",
    "compra": 1378577.1394333318,
    "venta": 1295690.4179330042
  },
  {
    "exchange": "belo",
    "moneda": "CHLt",
    "monedaBase": "BTC",
    "compra": 71066931.45659478,
    "venta": 66659709.13691909
  },
  {
    "exchange": "belo",
    "moneda": "COLt",
    "monedaBase": "BTC",
    "compra": 286601895.1486014,
    "venta": 268553575.27432317
  },
  {
    "exchange": "belo",
    "moneda": "BOLt",
    "monedaBase": "BTC",
    "compra": 790828.6942395808,
    "venta": 729874.39679847
  },
  {
    "exchange": "belo",
    "moneda": "ETH",
    "monedaBase": "BTC",
    "compra": 34.09048295987209,
    "venta": 33.404150131612354
  },
  {
    "exchange": "belo",
    "moneda": "USD",
    "monedaBase": "BTC",
    "criptomoneda": "USDT",
    "criptomonedaBase": null,
    "compra": 77146.4866,
    "venta": 75618.8235
  },
  {
    "exchange": "belo",
    "moneda": "USD",
    "monedaBase": "BTC",
    "criptomoneda": "USDC",
    "criptomonedaBase": null,
    "compra": 77138.1036,
    "venta": 75610.6065
  },
  {
    "exchange": "belo",
    "moneda": "SOL",
    "monedaBase": "BTC",
    "compra": 926.613164022576,
    "venta": 908.1810767758119
  },
  {
    "exchange": "belo",
    "moneda": "BRAt",
    "monedaBase": "BTC",
    "compra": 387269.126386,
    "venta": 374307.14871
  }
]