[
  {
    "exchange": "belo",
    "moneda": "ARS",
    "monedaBase": "BTC",
    "compra": 128176709.33,
    "venta": 123578896.32
  },
  {
    "exchange": "belo",
    "moneda": "ETH",
    "monedaBase": "BTC",
    "compra": 42.370008812961835,
    "venta": 41.51358532079623
  },
  {
    "exchange": "belo",
    "moneda": "USD",
    "monedaBase": "BTC",
    "criptomoneda": "USDT",
    "criptomonedaBase": null,
    "compra": 105062.8765,
    "venta": 102982.4136
  },
  {
    "exchange": "belo",
    "moneda": "USD",
    "monedaBase": "BTC",
    "criptomoneda": "USDC",
    "criptomonedaBase": null,
    "compra": 105112.72,
    "venta": 103031.2701
  },
  {
    "exchange": "belo",
    "moneda": "SOL",
    "monedaBase": "BTC",
    "compra": 684.7214005565415,
    "venta": 671.1170676479293
  }
]