[
  {
    "exchange": "belo",
    "moneda": "ARS",
    "monedaBase": "BTC",
    "compra": 122771499.9252,
    "venta": 118727224.704
  },
  {
    "exchange": "belo",
    "moneda": "BRAt",
    "monedaBase": "BTC",
    "compra": 406495.448814,
    "venta": 393606.56016
  },
  {
    "exchange": "belo",
    "moneda": "ARGt",
    "monedaBase": "BTC",
    "compra": 122771499.9252,
    "venta": 118727224.704
  },
  {
    "exchange": "belo",
    "moneda": "MEXt",
    "monedaBase": "BTC",
    "compra": 1444579.1472616987,
    "venta": 1357609.7439979129
  },
  {
    "exchange": "belo",
    "moneda": "CHLt",
    "monedaBase": "BTC",
    "compra": 75472541.48675017,
    "venta": 70792005.92702515
  },
  {
    "exchange": "belo",
    "moneda": "COLt",
    "monedaBase": "BTC",
    "compra": 315250370.5754207,
    "venta": 295404594.7921992
  },
  {
    "exchange": "belo",
    "moneda": "BOLt",
    "monedaBase": "BTC",
    "compra": 835125.9949826129,
    "venta": 782554.7697586506
  },
  {
    "exchange": "belo",
    "moneda": "ETH",
    "monedaBase": "BTC",
    "compra": 35.38007040634011,
    "venta": 34.667332279446434
  },
  {
    "exchange": "belo",
    "moneda": "USD",
    "monedaBase": "BTC",
    "criptomoneda": "USDT",
    "criptomonedaBase": null,
    "compra": 82286.5281,
    "venta": 80657.082
  },
  {
    "exchange": "belo",
    "moneda": "USD",
    "monedaBase": "BTC",
    "criptomoneda": "USDC",
    "criptomonedaBase": null,
    "compra": 82251.0973,
    "venta": 80622.3528
  },
  {
    "exchange": "belo",
    "moneda": "SOL",
    "monedaBase": "BTC",
    "compra": 847.5423813567797,
    "venta": 830.6896634793104
  },
  {
    "exchange": "belo",
    "moneda": "BRAt",
    "monedaBase": "BTC",
    "compra": 406495.448814,
    "venta": 393606.56016
  }
]