[
  {
    "exchange": "belo",
    "moneda": "ARS",
    "monedaBase": "BTC",
    "compra": 165077650.4224,
    "venta": 157961733.7815
  },
  {
    "exchange": "belo",
    "moneda": "ETH",
    "monedaBase": "BTC",
    "compra": 31.506581724922338,
    "venta": 30.87305924231338
  },
  {
    "exchange": "belo",
    "moneda": "USD",
    "monedaBase": "BTC",
    "criptomoneda": "USDT",
    "criptomonedaBase": null,
    "compra": 118932.0248,
    "venta": 116576.9253
  },
  {
    "exchange": "belo",
    "moneda": "USD",
    "monedaBase": "BTC",
    "criptomoneda": "USDC",
    "criptomonedaBase": null,
    "compra": 118938.2565,
    "venta": 116583.0336
  },
  {
    "exchange": "belo",
    "moneda": "SOL",
    "monedaBase": "BTC",
    "compra": 671.1188692452396,
    "venta": 657.7856828999403
  }
]