[
  {
    "exchange": "belo",
    "moneda": "ARS",
    "monedaBase": "USD",
    "criptomoneda": null,
    "criptomonedaBase": "USDT",
    "compra": 1309,
    "venta": 1284
  },
  {
    "exchange": "belo",
    "moneda": "ARS",
    "monedaBase": "USD",
    "criptomoneda": null,
    "criptomonedaBase": "USDC",
    "compra": 1310.83240365,
    "venta": 1281.8175852
  },
  {
    "exchange": "belo",
    "moneda": "ARS",
    "monedaBase": "USD",
    "criptomoneda": null,
    "criptomonedaBase": "USD_AR",
    "compra": 1338.4458077709612,
    "venta": 1245.392822502425
  },
  {
    "exchange": "dolarapp",
    "moneda": "ARS",
    "monedaBase": "USD",
    "criptomoneda": null,
    "criptomonedaBase": "USDC",
    "compra": 1288.39,
    "venta": 1272.6648
  },
  {
    "exchange": "satoshitango",
    "moneda": "ARS",
    "monedaBase": "USD",
    "criptomoneda": null,
    "criptomonedaBase": "USDT",
    "compra": 1286.32,
    "venta": null
  },
  {
    "exchange": "satoshitango",
    "moneda": "ARS",
    "monedaBase": "USD",
    "criptomoneda": null,
    "criptomonedaBase": "USD",
    "compra": 1257.4,
    "venta": null
  }
]