[
  {
    "exchange": "belo",
    "moneda": "ARS",
    "monedaBase": "USD",
    "criptomoneda": null,
    "criptomonedaBase": "USDT",
    "compra": 1215,
    "venta": 1195
  },
  {
    "exchange": "belo",
    "moneda": "ARS",
    "monedaBase": "USD",
    "criptomoneda": null,
    "criptomonedaBase": "USDC",
    "compra": 1216.8225,
    "venta": 1193.08817925
  },
  {
    "exchange": "belo",
    "moneda": "ARS",
    "monedaBase": "USD",
    "criptomoneda": null,
    "criptomonedaBase": "USD_AR",
    "compra": 1215,
    "venta": 1153.4749034749034
  },
  {
    "exchange": "dolarapp",
    "moneda": "ARS",
    "monedaBase": "USD",
    "criptomoneda": null,
    "criptomonedaBase": "USDC",
    "compra": 1203.72,
    "venta": 1188.0297
  },
  {
    "exchange": "satoshitango",
    "moneda": "ARS",
    "monedaBase": "USD",
    "criptomoneda": null,
    "criptomonedaBase": "USDT",
    "compra": 1212.69,
    "venta": null
  },
  {
    "exchange": "satoshitango",
    "moneda": "ARS",
    "monedaBase": "USD",
    "criptomoneda": null,
    "criptomonedaBase": "USD",
    "compra": 1156.04,
    "venta": null
  }
]