[
  {
    "moneda": "USD",
    "casa": "oficial",
    "nombre": "Dólar",
    "compra": 1290,
    "venta": 1340,
    "fechaActualizacion": "2025-08-08T12:50:00.000Z"
  },
  {
    "moneda": "EUR",
    "casa": "oficial",
    "nombre": "Euro",
    "compra": 1531.5938,
    "venta": 1545.3725,
    "fechaActualizacion": "2025-08-08T12:50:00.000Z"
  },
  {
    "moneda": "BRL",
    "casa": "oficial",
    "nombre": "Real Brasileño",
    "compra": 244.3809,
    "venta": 244.5143,
    "fechaActualizacion": "2025-08-08T12:50:00.000Z"
  },
  {
    "moneda": "CLP",
    "casa": "oficial",
    "nombre": "Peso Chileno",
    "compra": 1.3748,
    "venta": 1.3748,
    "fechaActualizacion": "2025-08-08T12:50:00.000Z"
  },
  {
    "moneda": "UYU",
    "casa": "oficial",
    "nombre": "Peso Uruguayo",
    "compra": 33.0585,
    "venta": 33.0587,
    "fechaActualizacion": "2025-08-08T12:50:00.000Z"
  }
]