[
  {
    "exchange": "belo",
    "moneda": "ARS",
    "monedaBase": "USD",
    "criptomoneda": null,
    "criptomonedaBase": "USDT",
    "compra": 1235,
    "venta": 1218
  },
  {
    "exchange": "belo",
    "moneda": "ARS",
    "monedaBase": "USD",
    "criptomoneda": null,
    "criptomonedaBase": "USDC",
    "compra": 1238.21303775,
    "venta": 1217.389173
  },
  {
    "exchange": "belo",
    "moneda": "USD",
    "monedaBase": "USD",
    "criptomoneda": "USDC",
    "criptomonedaBase": "USDT",
    "compra": 1.0005017516284416,
    "venta": 0.9974051010189341
  },
  {
    "exchange": "belo",
    "moneda": "USD",
    "monedaBase": "USD",
    "criptomoneda": "USDT",
    "criptomonedaBase": "USD",
    "compra": 1,
    "venta": 1
  },
  {
    "exchange": "belo",
    "moneda": "USD",
    "monedaBase": "USD",
    "criptomoneda": "USD_AR",
    "criptomonedaBase": "USDT",
    "compra": 1.031,
    "venta": 0.99
  },
  {
    "exchange": "belo",
    "moneda": "ARS",
    "monedaBase": "USD",
    "criptomoneda": null,
    "criptomonedaBase": "USD_AR",
    "compra": 1247.4747474747476,
    "venta": 1181.3773035887489
  }
]