[
  {
    "exchange": "belo",
    "moneda": "ARS",
    "monedaBase": "USD",
    "criptomoneda": null,
    "criptomonedaBase": "USDT",
    "compra": 1560,
    "venta": 1538
  },
  {
    "exchange": "belo",
    "moneda": "ARS",
    "monedaBase": "USD",
    "criptomoneda": null,
    "criptomonedaBase": "USDC",
    "compra": 1563.90234,
    "venta": 1537.0751237
  },
  {
    "exchange": "belo",
    "moneda": "ARGt",
    "monedaBase": "USD",
    "criptomoneda": null,
    "criptomonedaBase": "USDT",
    "compra": 1560,
    "venta": 1538
  },
  {
    "exchange": "belo",
    "moneda": "ARGt",
    "monedaBase": "USD",
    "criptomoneda": null,
    "criptomonedaBase": "USDC",
    "compra": 1563.90234,
    "venta": 1537.0751237
  },
  {
    "exchange": "belo",
    "moneda": "USD",
    "monedaBase": "USD",
    "criptomoneda": "USDC",
    "criptomonedaBase": "USDT",
    "compra": 1.0006017118394146,
    "venta": 0.9975047418881667
  },
  {
    "exchange": "belo",
    "moneda": "SOL",
    "monedaBase": "USD",
    "criptomoneda": null,
    "criptomonedaBase": "USDT",
    "compra": 0.008130894390252033,
    "venta": 0.007969245089351176
  },
  {
    "exchange": "belo",
    "moneda": "BRLa",
    "monedaBase": "USD",
    "criptomoneda": null,
    "criptomonedaBase": "USDT",
    "compra": 5.62,
    "venta": 5.54
  },
  {
    "exchange": "belo",
    "moneda": "SOL",
    "monedaBase": "USD",
    "criptomoneda": null,
    "criptomonedaBase": "USDC",
    "compra": 0.008138756023696802,
    "venta": 0.007976949805841042
  },
  {
    "exchange": "belo",
    "moneda": "BRLa",
    "monedaBase": "USD",
    "criptomoneda": null,
    "criptomonedaBase": "USDC",
    "compra": 5.63405843,
    "venta": 5.536668521
  },
  {
    "exchange": "belo",
    "moneda": "USD",
    "monedaBase": "USD",
    "criptomoneda": "USDT",
    "criptomonedaBase": "USD",
    "compra": 1,
    "venta": 1
  },
  {
    "exchange": "belo",
    "moneda": "USD",
    "monedaBase": "USD",
    "criptomoneda": "USD_AR",
    "criptomonedaBase": "USDT",
    "compra": 1.052,
    "venta": 1.025
  },
  {
    "exchange": "belo",
    "moneda": "ARS",
    "monedaBase": "USD",
    "criptomoneda": null,
    "criptomonedaBase": "USD_AR",
    "compra": 1521.9512195121952,
    "venta": 1461.9771863117871
  }
]