[
  {
    "exchange": "belo",
    "moneda": "ARS",
    "monedaBase": "USD",
    "criptomoneda": null,
    "criptomonedaBase": "USDT",
    "compra": 1385,
    "venta": 1362
  },
  {
    "exchange": "belo",
    "moneda": "ARS",
    "monedaBase": "USD",
    "criptomoneda": null,
    "criptomonedaBase": "USDC",
    "compra": 1387.0775,
    "venta": 1359.8210043
  },
  {
    "exchange": "belo",
    "moneda": "USD",
    "monedaBase": "USD",
    "criptomoneda": "USDC",
    "criptomonedaBase": "USDT",
    "compra": 1.0016024136214323,
    "venta": 0.9985022466300549
  },
  {
    "exchange": "belo",
    "moneda": "SOL",
    "monedaBase": "USD",
    "criptomoneda": null,
    "criptomonedaBase": "USDT",
    "compra": 0.005260942760942761,
    "venta": 0.005156497109009896
  },
  {
    "exchange": "belo",
    "moneda": "SOL",
    "monedaBase": "USD",
    "criptomoneda": null,
    "criptomonedaBase": "USDC",
    "compra": 0.005258751614436745,
    "venta": 0.00515434957520428
  },
  {
    "exchange": "belo",
    "moneda": "USD",
    "monedaBase": "USD",
    "criptomoneda": "USDT",
    "criptomonedaBase": "USD",
    "compra": 1,
    "venta": 1
  },
  {
    "exchange": "belo",
    "moneda": "USD",
    "monedaBase": "USD",
    "criptomoneda": "USD_AR",
    "criptomonedaBase": "USDT",
    "compra": 1.023,
    "venta": 0.98999
  },
  {
    "exchange": "belo",
    "moneda": "ARS",
    "monedaBase": "USD",
    "criptomoneda": null,
    "criptomonedaBase": "USD_AR",
    "compra": 1399.0040303437409,
    "venta": 1331.3782991202347
  }
]