[
  {
    "exchange": "belo",
    "moneda": "ARS",
    "monedaBase": "ETH",
    "compra": 3063136.08,
    "venta": 2951622.0261
  },
  {
    "exchange": "belo",
    "moneda": "USD",
    "monedaBase": "ETH",
    "criptomoneda": "USDT",
    "criptomonedaBase": null,
    "compra": 2593.68,
    "venta": 2542.3101
  },
  {
    "exchange": "belo",
    "moneda": "USD",
    "monedaBase": "ETH",
    "criptomoneda": "USDC",
    "criptomonedaBase": null,
    "compra": 2594.7001,
    "venta": 2543.31
  },
  {
    "exchange": "belo",
    "moneda": "SOL",
    "monedaBase": "ETH",
    "compra": 14.930636506974343,
    "venta": 14.344305407290216
  }
]