[
  {
    "exchange": "belo",
    "moneda": "ARS",
    "monedaBase": "ETH",
    "compra": 2977057.315,
    "venta": 2868424.3665
  },
  {
    "exchange": "belo",
    "moneda": "USD",
    "monedaBase": "ETH",
    "criptomoneda": "USDT",
    "criptomonedaBase": null,
    "compra": 2533.6658,
    "venta": 2483.4843
  },
  {
    "exchange": "belo",
    "moneda": "USD",
    "monedaBase": "ETH",
    "criptomoneda": "USDC",
    "criptomonedaBase": null,
    "compra": 2534.7566,
    "venta": 2484.5535
  },
  {
    "exchange": "belo",
    "moneda": "SOL",
    "monedaBase": "ETH",
    "compra": 14.85436405965746,
    "venta": 14.271011877740298
  }
]