[
  {
    "exchange": "belo",
    "moneda": "ARS",
    "monedaBase": "ETH",
    "compra": 3429654.7982,
    "venta": 3301988.6592
  },
  {
    "exchange": "belo",
    "moneda": "DAI",
    "monedaBase": "ETH",
    "compra": 2774.47437835,
    "venta": 2711.10688539768
  },
  {
    "exchange": "belo",
    "moneda": "USD",
    "monedaBase": "ETH",
    "criptomoneda": "USDT",
    "criptomonedaBase": null,
    "compra": 2770.3189,
    "venta": 2715.4512
  },
  {
    "exchange": "belo",
    "moneda": "USD",
    "monedaBase": "ETH",
    "criptomoneda": "USDC",
    "criptomonedaBase": null,
    "compra": 2770.8542,
    "venta": 2715.9759
  }
]