[
  {
    "exchange": "belo",
    "moneda": "ARS",
    "monedaBase": "ETH",
    "compra": 3323104.828,
    "venta": 3215469.609
  },
  {
    "exchange": "belo",
    "moneda": "BRAt",
    "monedaBase": "ETH",
    "compra": 11383.879377,
    "venta": 11026.35369
  },
  {
    "exchange": "belo",
    "moneda": "ARGt",
    "monedaBase": "ETH",
    "compra": 3323104.828,
    "venta": 3215469.609
  },
  {
    "exchange": "belo",
    "moneda": "MEXt",
    "monedaBase": "ETH",
    "compra": 39623.99552799054,
    "venta": 37246.33221576082
  },
  {
    "exchange": "belo",
    "moneda": "CHLt",
    "monedaBase": "ETH",
    "compra": 2046764.7833702725,
    "venta": 1919739.0861700128
  },
  {
    "exchange": "belo",
    "moneda": "COLt",
    "monedaBase": "ETH",
    "compra": 8317890.324689475,
    "venta": 7793980.141580325
  },
  {
    "exchange": "belo",
    "moneda": "BOLt",
    "monedaBase": "ETH",
    "compra": 21276.404476219548,
    "venta": 19636.408497235483
  },
  {
    "exchange": "belo",
    "moneda": "USD",
    "monedaBase": "ETH",
    "criptomoneda": "USDT",
    "criptomonedaBase": null,
    "compra": 2245.3411,
    "venta": 2200.869
  },
  {
    "exchange": "belo",
    "moneda": "USD",
    "monedaBase": "ETH",
    "criptomoneda": "USDC",
    "criptomonedaBase": null,
    "compra": 2245.0381,
    "venta": 2200.572
  },
  {
    "exchange": "belo",
    "moneda": "SOL",
    "monedaBase": "ETH",
    "compra": 26.952124933230102,
    "venta": 25.892089090087715
  },
  {
    "exchange": "belo",
    "moneda": "BRAt",
    "monedaBase": "ETH",
    "compra": 11383.879377,
    "venta": 11026.35369
  }
]