[
  {
    "moneda": "USD",
    "nombre": "Dólar",
    "compra": 37.5,
    "venta": 39.7,
    "fechaActualizacion": "2026-02-04T15:01:23.141Z"
  },
  {
    "moneda": "EUR",
    "nombre": "Euro",
    "compra": 43.24,
    "venta": 48.25,
    "fechaActualizacion": "2026-02-04T15:01:23.142Z"
  },
  {
    "moneda": "ARS",
    "nombre": "Peso Argentino",
    "compra": 0.02,
    "venta": 0.2,
    "fechaActualizacion": "2026-02-04T15:01:23.142Z"
  },
  {
    "moneda": "BRL",
    "nombre": "Real",
    "compra": 6.9,
    "venta": 8.6,
    "fechaActualizacion": "2026-02-04T15:01:23.142Z"
  },
  {
    "moneda": "GBP",
    "nombre": "Libra Esterlina",
    "compra": 50.15,
    "venta": 56.46,
    "fechaActualizacion": "2026-02-04T15:01:23.142Z"
  },
  {
    "moneda": "CHF",
    "nombre": "Franco Suizo",
    "compra": 47.45,
    "venta": 52.09,
    "fechaActualizacion": "2026-02-04T15:01:23.143Z"
  },
  {
    "moneda": "PYG",
    "nombre": "Guaraní",
    "compra": 0.00555,
    "venta": 0.00612,
    "fechaActualizacion": "2026-02-04T15:01:23.143Z"
  },
  {
    "moneda": "UI",
    "nombre": "Unidad Indexada",
    "compra": null,
    "venta": 6.4193,
    "fechaActualizacion": "2026-02-04T15:01:23.143Z"
  },
  {
    "moneda": "XAU",
    "nombre": "Onza Troy De Oro",
    "compra": 184215,
    "venta": 202154.385,
    "fechaActualizacion": "2026-02-04T15:01:23.143Z"
  }
]