[
  {
    "exchange": "belo",
    "moneda": "ARS",
    "monedaBase": "BRL",
    "compra": 305.8496015936255,
    "venta": 289.78388998035365
  },
  {
    "exchange": "fiwind",
    "moneda": "ARS",
    "monedaBase": "BRL",
    "compra": 303.422109,
    "venta": 283.039226
  },
  {
    "exchange": "dolarapp",
    "moneda": "ARS",
    "monedaBase": "BRL",
    "compra": 297.4864667355599,
    "venta": null
  },
  {
    "exchange": "satoshitango",
    "moneda": "ARS",
    "monedaBase": "BRL",
    "compra": 301.19,
    "venta": null
  },
  {
    "exchange": "prex",
    "moneda": "ARS",
    "monedaBase": "BRL",
    "compra": 307.073,
    "venta": null
  },
  {
    "exchange": "lemon",
    "moneda": "ARS",
    "monedaBase": "BRL",
    "compra": 304.49,
    "venta": null
  },
  {
    "exchange": "plus",
    "moneda": "ARS",
    "monedaBase": "BRL",
    "compra": 302.24,
    "venta": null
  },
  {
    "exchange": "astropay",
    "moneda": "ARS",
    "monedaBase": "BRL",
    "compra": 297.35735125,
    "venta": null
  }
]