[
  {
    "exchange": "belo",
    "moneda": "ARS",
    "monedaBase": "BRL",
    "compra": 304.99415322580643,
    "venta": 288.8667992047714
  },
  {
    "exchange": "fiwind",
    "moneda": "ARS",
    "monedaBase": "BRL",
    "compra": 301.342164,
    "venta": 281.440288
  },
  {
    "exchange": "dolarapp",
    "moneda": "ARS",
    "monedaBase": "BRL",
    "compra": 291.58990878870964,
    "venta": null
  },
  {
    "exchange": "satoshitango",
    "moneda": "ARS",
    "monedaBase": "BRL",
    "compra": 296.37,
    "venta": null
  },
  {
    "exchange": "prex",
    "moneda": "ARS",
    "monedaBase": "BRL",
    "compra": 303.6424,
    "venta": null
  },
  {
    "exchange": "lemon",
    "moneda": "ARS",
    "monedaBase": "BRL",
    "compra": 302.06,
    "venta": null
  },
  {
    "exchange": "plus",
    "moneda": "ARS",
    "monedaBase": "BRL",
    "compra": 301.58,
    "venta": null
  },
  {
    "exchange": "astropay",
    "moneda": "ARS",
    "monedaBase": "BRL",
    "compra": 294.98011778,
    "venta": null
  }
]