[
  {
    "exchange": "belo",
    "moneda": "ARS",
    "monedaBase": "BRL",
    "compra": 290.55126213592234,
    "venta": 276.3915547024952
  },
  {
    "exchange": "fiwind",
    "moneda": "ARS",
    "monedaBase": "BRL",
    "compra": 288.853495,
    "venta": 268.606169
  },
  {
    "exchange": "dolarapp",
    "moneda": "ARS",
    "monedaBase": "BRL",
    "compra": 282.04341844999607,
    "venta": null
  },
  {
    "exchange": "satoshitango",
    "moneda": "ARS",
    "monedaBase": "BRL",
    "compra": 285.39,
    "venta": null
  },
  {
    "exchange": "prex",
    "moneda": "ARS",
    "monedaBase": "BRL",
    "compra": 287.8512,
    "venta": null
  },
  {
    "exchange": "lemon",
    "moneda": "ARS",
    "monedaBase": "BRL",
    "compra": 291.89,
    "venta": null
  },
  {
    "exchange": "plus",
    "moneda": "ARS",
    "monedaBase": "BRL",
    "compra": 288.5,
    "venta": null
  },
  {
    "exchange": "astropay",
    "moneda": "ARS",
    "monedaBase": "BRL",
    "compra": 279.33123155,
    "venta": null
  }
]