[
  {
    "exchange": "belo",
    "moneda": "ARS",
    "monedaBase": "BRL",
    "compra": 241.22039116262224,
    "venta": 223.05545866759678
  },
  {
    "exchange": "fiwind",
    "moneda": "ARS",
    "monedaBase": "BRL",
    "compra": 235.322418,
    "venta": 222.323025
  },
  {
    "exchange": "cocos",
    "moneda": "ARS",
    "monedaBase": "BRL",
    "compra": 229.98179614947784,
    "venta": null
  },
  {
    "exchange": "dolarapp",
    "moneda": "ARS",
    "monedaBase": "BRL",
    "compra": 232.5160753559597,
    "venta": null
  },
  {
    "exchange": "satoshitango",
    "moneda": "ARS",
    "monedaBase": "BRL",
    "compra": 239.14,
    "venta": null
  },
  {
    "exchange": "prex",
    "moneda": "ARS",
    "monedaBase": "BRL",
    "compra": 230.8068,
    "venta": null
  },
  {
    "exchange": "lemon",
    "moneda": "ARS",
    "monedaBase": "BRL",
    "compra": 236.07,
    "venta": null
  },
  {
    "exchange": "plus",
    "moneda": "ARS",
    "monedaBase": "BRL",
    "compra": 236.41,
    "venta": null
  },
  {
    "exchange": "astropay",
    "moneda": "ARS",
    "monedaBase": "BRL",
    "compra": 229.75355417,
    "venta": null
  }
]