[
  {
    "exchange": "belo",
    "moneda": "USD",
    "monedaBase": "ARS",
    "criptomoneda": "USDT",
    "criptomonedaBase": null,
    "compra": 0.000663129973474801,
    "venta": 0.0006711409395973154
  },
  {
    "exchange": "belo",
    "moneda": "USD",
    "monedaBase": "ARS",
    "criptomoneda": "USDC",
    "criptomonedaBase": null,
    "compra": 0.0006613431565344762,
    "venta": 0.0006714106116694925
  },
  {
    "exchange": "belo",
    "moneda": "USD",
    "monedaBase": "ARS",
    "criptomoneda": "USD_AR",
    "criptomonedaBase": null,
    "compra": 0.0006750663129973474,
    "venta": 0.0006993288590604027
  },
  {
    "exchange": "dolarapp",
    "moneda": "USD",
    "monedaBase": "ARS",
    "criptomoneda": "USDC",
    "criptomonedaBase": null,
    "compra": 0.0006699987940021709,
    "venta": 0.0006716324483366889
  },
  {
    "exchange": "satoshitango",
    "moneda": "USD",
    "monedaBase": "ARS",
    "criptomoneda": "USDT",
    "criptomonedaBase": null,
    "compra": 0.0006734460233012323,
    "venta": null
  },
  {
    "exchange": "satoshitango",
    "moneda": "USD",
    "monedaBase": "ARS",
    "criptomoneda": "USD",
    "criptomonedaBase": null,
    "compra": 0.0007084711900190579,
    "venta": null
  }
]