[
  {
    "exchange": "belo",
    "moneda": "USD",
    "monedaBase": "ARS",
    "criptomoneda": "USDT",
    "criptomonedaBase": null,
    "compra": 0.0008438818565400844,
    "venta": 0.000864304235090752
  },
  {
    "exchange": "belo",
    "moneda": "USD",
    "monedaBase": "ARS",
    "criptomoneda": "USDC",
    "criptomonedaBase": null,
    "compra": 0.0008428707908828808,
    "venta": 0.0008659490186567887
  },
  {
    "exchange": "belo",
    "moneda": "USD",
    "monedaBase": "ARS",
    "criptomoneda": "USD_AR",
    "criptomonedaBase": null,
    "compra": 0.0008573839662447258,
    "venta": 0.000909248055315471
  },
  {
    "exchange": "dolarapp",
    "moneda": "USD",
    "monedaBase": "ARS",
    "criptomoneda": "USDC",
    "criptomonedaBase": null,
    "compra": 0.0008540511918284381,
    "venta": 0.0008638879710079198
  },
  {
    "exchange": "satoshitango",
    "moneda": "USD",
    "monedaBase": "ARS",
    "criptomoneda": "USDT",
    "criptomonedaBase": null,
    "compra": 0.0008609111884018045,
    "venta": null
  },
  {
    "exchange": "satoshitango",
    "moneda": "USD",
    "monedaBase": "ARS",
    "criptomoneda": "USD",
    "criptomonedaBase": null,
    "compra": 0.0009013718880135566,
    "venta": null
  }
]