[
  {
    "exchange": "belo",
    "moneda": "USD",
    "monedaBase": "ARS",
    "criptomoneda": "USDT",
    "criptomonedaBase": null,
    "compra": 0.000641025641025641,
    "venta": 0.0006493506493506494
  },
  {
    "exchange": "belo",
    "moneda": "USD",
    "monedaBase": "ARS",
    "criptomoneda": "USDC",
    "criptomonedaBase": null,
    "compra": 0.000639809618864028,
    "venta": 0.0006501310992287184
  },
  {
    "exchange": "belo",
    "moneda": "USD",
    "monedaBase": "ARS",
    "criptomoneda": "USD_AR",
    "criptomonedaBase": null,
    "compra": 0.0006551282051282052,
    "venta": 0.0006837662337662337
  },
  {
    "exchange": "dolarapp",
    "moneda": "USD",
    "monedaBase": "ARS",
    "criptomoneda": "USDC",
    "criptomonedaBase": null,
    "compra": 0.0006501950585175553,
    "venta": 0.0006521476555940668
  },
  {
    "exchange": "satoshitango",
    "moneda": "USD",
    "monedaBase": "ARS",
    "criptomoneda": "USDT",
    "criptomonedaBase": null,
    "compra": 0.0006543132328308208,
    "venta": null
  },
  {
    "exchange": "satoshitango",
    "moneda": "USD",
    "monedaBase": "ARS",
    "criptomoneda": "USD",
    "criptomonedaBase": null,
    "compra": 0.0006876822357924849,
    "venta": null
  }
]