[
  {
    "moeda": "ARS",
    "nome": "Peso Argentino",
    "compra": 0.0036,
    "venda": 0.0036,
    "fechoAnterior": 0.0036,
    "dataAtualizacao": "2026-02-09T12:01:34.761Z"
  },
  {
    "moeda": "USD",
    "nome": "Dólar",
    "compra": 5.217,
    "venda": 5.219,
    "fechoAnterior": 5.2166,
    "dataAtualizacao": "2026-02-06T13:01:00.000Z"
  },
  {
    "moeda": "EUR",
    "nome": "Euro",
    "compra": 6.1881,
    "venda": 6.2035,
    "fechoAnterior": 6.165,
    "dataAtualizacao": "2026-02-09T12:01:47.004Z"
  },
  {
    "moeda": "CLP",
    "nome": "Peso Chileno",
    "compra": 0.006094,
    "venda": 0.006096,
    "fechoAnterior": 0.006095,
    "dataAtualizacao": "2026-02-09T12:01:52.262Z"
  },
  {
    "moeda": "UYU",
    "nome": "Peso Uruguayo",
    "compra": 0.1354,
    "venda": 0.1354,
    "fechoAnterior": 0.1361,
    "dataAtualizacao": "2026-02-09T12:01:57.949Z"
  }
]