[
  {
    "moeda": "ARS",
    "nome": "Peso Argentino",
    "compra": 0.0051,
    "venda": 0.0051,
    "fechoAnterior": 0.0049,
    "dataAtualizacao": "2025-04-16T16:59:35.607Z"
  },
  {
    "moeda": "USD",
    "nome": "Dólar",
    "compra": 5.863,
    "venda": 5.865,
    "fechoAnterior": 5.8859,
    "dataAtualizacao": "2025-04-16T17:02:07.777Z"
  },
  {
    "moeda": "EUR",
    "nome": "Euro",
    "compra": 6.6534,
    "venda": 6.6711,
    "fechoAnterior": 6.6489,
    "dataAtualizacao": "2025-04-16T16:56:34.000Z"
  },
  {
    "moeda": "CLP",
    "nome": "Peso Chileno",
    "compra": 0.006064,
    "venda": 0.006067,
    "fechoAnterior": 0.006063,
    "dataAtualizacao": "2025-04-16T17:00:07.576Z"
  },
  {
    "moeda": "UYU",
    "nome": "Peso Uruguayo",
    "compra": 0.1385,
    "venda": 0.1385,
    "fechoAnterior": 0.1378,
    "dataAtualizacao": "2025-04-16T17:00:07.576Z"
  }
]