[
  {
    "moeda": "ARS",
    "nome": "Peso Argentino",
    "compra": 0.006,
    "venda": 0.006,
    "fechoAnterior": 0.006,
    "dataAtualizacao": "2024-12-30T18:14:30.000Z"
  },
  {
    "moeda": "USD",
    "nome": "Dólar",
    "compra": 6.1896,
    "venda": 6.1909,
    "fechoAnterior": 6.1964,
    "dataAtualizacao": "2024-12-30T18:52:28.000Z"
  },
  {
    "moeda": "EUR",
    "nome": "Euro",
    "compra": 6.4309,
    "venda": 6.4475,
    "fechoAnterior": 6.4538,
    "dataAtualizacao": "2024-12-30T18:49:41.000Z"
  },
  {
    "moeda": "CLP",
    "nome": "Peso Chileno",
    "compra": 0.006231,
    "venda": 0.006233,
    "fechoAnterior": 0.00624,
    "dataAtualizacao": "2024-12-30T18:28:15.000Z"
  },
  {
    "moeda": "UYU",
    "nome": "Peso Uruguayo",
    "compra": 0.141,
    "venda": 0.1411,
    "fechoAnterior": 0.1407,
    "dataAtualizacao": "2024-12-30T19:00:20.000Z"
  }
]