[
  {
    "exchange": "belo",
    "moneda": "ARS",
    "monedaBase": "COLt",
    "compra": 0.42126019685982774,
    "venta": 0.39252561764705884
  },
  {
    "exchange": "belo",
    "moneda": "BRAt",
    "monedaBase": "COLt",
    "compra": 0.0014164274536077263,
    "venta": 0.0013190779411764706
  },
  {
    "exchange": "belo",
    "moneda": "ARGt",
    "monedaBase": "COLt",
    "compra": 0.42126019685982774,
    "venta": 0.39252561764705884
  },
  {
    "exchange": "belo",
    "moneda": "MEXt",
    "monedaBase": "COLt",
    "compra": 0.005026550957032958,
    "venta": 0.004551746136901765
  },
  {
    "exchange": "belo",
    "moneda": "CHLt",
    "monedaBase": "COLt",
    "compra": 0.2593493741856725,
    "venta": 0.23440508941442353
  },
  {
    "exchange": "belo",
    "moneda": "COLt",
    "monedaBase": "COLt",
    "compra": 1,
    "venta": 1
  },
  {
    "exchange": "belo",
    "moneda": "BOLt",
    "monedaBase": "COLt",
    "compra": 0.002837708237388204,
    "venta": 0.0025234477986666665
  }
]