[
  {
    "exchange": "belo",
    "moneda": "USD",
    "monedaBase": "BRAt",
    "criptomoneda": "USDT",
    "criptomonedaBase": null,
    "compra": 0.19011406844106465,
    "venta": 0.1923076923076923
  },
  {
    "exchange": "belo",
    "moneda": "USD",
    "monedaBase": "BRAt",
    "criptomoneda": "USDC",
    "criptomonedaBase": null,
    "compra": 0.1898483092853116,
    "venta": 0.19263511421131727
  },
  {
    "exchange": "belo",
    "moneda": "USD",
    "monedaBase": "BRAt",
    "criptomoneda": "USDT",
    "criptomonedaBase": null,
    "compra": 0.19011406844106465,
    "venta": 0.1923076923076923
  },
  {
    "exchange": "belo",
    "moneda": "USD",
    "monedaBase": "BRAt",
    "criptomoneda": "USDC",
    "criptomonedaBase": null,
    "compra": 0.1898483092853116,
    "venta": 0.19263511421131727
  }
]